spannercli/__init__.py
spannercli/commands.py
spannercli/completion.py
spannercli/lexer.py
spannercli/main.py
spannercli/queryutils.py
spannercli/structures.py
spannercli/config/__init__.py
spannercli/config/constant.py
spannercli/config/env.py
spanner_cli-0.19.1.dist-info/LICENSE
spanner_cli-0.19.1.dist-info/METADATA
spanner_cli-0.19.1.dist-info/WHEEL
spanner_cli-0.19.1.dist-info/entry_points.txt
spanner_cli-0.19.1.dist-info/top_level.txt
spanner_cli-0.19.1.dist-info/RECORD
