Metadata-Version: 2.1
Name: spanner-cli
Version: 0.19.1
Summary: A Python cli REPL client for Google Cloud Spanner.
Home-page: https://github.com/shoma/spanner-cli
Author: Shoma Suzuki
Author-email: shoma@catbot.net
License: MIT
Classifier: Intended Audience :: Developers
Classifier: Development Status :: 7 - Inactive
Classifier: Environment :: Console
Classifier: License :: OSI Approved :: MIT License
Classifier: Programming Language :: Python
Classifier: Programming Language :: Python :: 3
Classifier: Programming Language :: Python :: 3.7
Classifier: Programming Language :: Python :: 3.8
Classifier: Programming Language :: Python :: 3.9
Classifier: Programming Language :: SQL
Classifier: Topic :: Database
Requires-Python: >=3.6
License-File: LICENSE
Requires-Dist: google-cloud-spanner
Requires-Dist: prompt-toolkit
Requires-Dist: cli-helpers
Requires-Dist: pygments
Requires-Dist: click
